{
  "location": {
    "city": "Toronto",
    "country": "Canada",
    "latitude": 43.6532,
    "longitude": -79.3832
  },
  "extraction_info": {
    "timestamp": "2026-01-01T09:37:48.429067",
    "current_available": true,
    "forecast_days": 7,
    "source": "Open-Meteo API"
  },
  "current_weather": {
    "timestamp": "2026-01-01T04:30",
    "city": "Toronto",
    "country": "Canada",
    "latitude": 43.6532,
    "longitude": -79.3832,
    "temperature": -14.3,
    "feels_like": -19.7,
    "humidity": 74,
    "precipitation": 0.0,
    "weather_code": 1,
    "wind_speed": 11.5,
    "wind_direction": 309,
    "extracted_at": "2026-01-01T09:37:47.779769"
  },
  "current_analysis": {
    "temperature_celsius": -14.3,
    "temperature_fahrenheit": 6.3,
    "feels_like_celsius": -19.7,
    "feels_like_fahrenheit": -3.5,
    "humidity_level": "High",
    "weather_description": "Mainly clear",
    "wind_description": "Light breeze",
    "comfort_index": "Uncomfortable",
    "precipitation_status": "No"
  },
  "forecast_data": [
    {
      "date": "2026-01-01",
      "city": "Toronto",
      "country": "Canada",
      "temp_max": -7.0,
      "temp_min": -15.0,
      "precipitation": 0.2,
      "weather_code": 71,
      "wind_speed_max": 23.5,
      "wind_direction": 255,
      "extracted_at": "2026-01-01T09:37:48.428092"
    },
    {
      "date": "2026-01-02",
      "city": "Toronto",
      "country": "Canada",
      "temp_max": -4.7,
      "temp_min": -9.9,
      "precipitation": 0.0,
      "weather_code": 3,
      "wind_speed_max": 22.3,
      "wind_direction": 247,
      "extracted_at": "2026-01-01T09:37:48.428106"
    },
    {
      "date": "2026-01-03",
      "city": "Toronto",
      "country": "Canada",
      "temp_max": -5.4,
      "temp_min": -10.6,
      "precipitation": 0.3,
      "weather_code": 71,
      "wind_speed_max": 22.8,
      "wind_direction": 289,
      "extracted_at": "2026-01-01T09:37:48.428109"
    },
    {
      "date": "2026-01-04",
      "city": "Toronto",
      "country": "Canada",
      "temp_max": -3.7,
      "temp_min": -6.4,
      "precipitation": 0.9,
      "weather_code": 71,
      "wind_speed_max": 18.0,
      "wind_direction": 282,
      "extracted_at": "2026-01-01T09:37:48.428112"
    },
    {
      "date": "2026-01-05",
      "city": "Toronto",
      "country": "Canada",
      "temp_max": -0.5,
      "temp_min": -6.8,
      "precipitation": 2.8,
      "weather_code": 71,
      "wind_speed_max": 14.3,
      "wind_direction": 246,
      "extracted_at": "2026-01-01T09:37:48.428115"
    },
    {
      "date": "2026-01-06",
      "city": "Toronto",
      "country": "Canada",
      "temp_max": 3.1,
      "temp_min": -1.6,
      "precipitation": 0.0,
      "weather_code": 45,
      "wind_speed_max": 18.2,
      "wind_direction": 215,
      "extracted_at": "2026-01-01T09:37:48.428117"
    },
    {
      "date": "2026-01-07",
      "city": "Toronto",
      "country": "Canada",
      "temp_max": 3.1,
      "temp_min": 0.9,
      "precipitation": 0.0,
      "weather_code": 45,
      "wind_speed_max": 18.2,
      "wind_direction": 247,
      "extracted_at": "2026-01-01T09:37:48.428120"
    }
  ],
  "forecast_analysis": {
    "temperature_trend": "Warming trend",
    "temperature_range": {
      "highest": 3.1,
      "lowest": -15.0,
      "average_high": -2.2,
      "average_low": -7.1
    },
    "precipitation_forecast": {
      "total_expected": 4.2,
      "rainy_days": 4,
      "heaviest_day": 2.8
    },
    "weather_summary": "1 cloudy day, 4 rainy days, 4 snowy days",
    "alerts": [
      "Very cold weather expected on 2026-01-01: -15.0°C",
      "Very cold weather expected on 2026-01-03: -10.6°C"
    ]
  },
  "transformation_timestamp": "2026-01-01T09:37:48.429695",
  "data_quality": {
    "current_available": true,
    "forecast_available": true,
    "forecast_days": 7,
    "completeness": "Good"
  },
  "recorded_at": "2026-01-01T09:37:48.429816"
}