{
  "location": {
    "city": "Toronto",
    "country": "Canada",
    "latitude": 43.6532,
    "longitude": -79.3832
  },
  "extraction_info": {
    "timestamp": "2025-09-08T07:18:35.019484",
    "current_available": true,
    "forecast_days": 7,
    "source": "Open-Meteo API"
  },
  "current_weather": {
    "timestamp": "2025-09-08T03:15",
    "city": "Toronto",
    "country": "Canada",
    "latitude": 43.6532,
    "longitude": -79.3832,
    "temperature": 9.5,
    "feels_like": 8.7,
    "humidity": 83,
    "precipitation": 0.0,
    "weather_code": 0,
    "wind_speed": 11.7,
    "wind_direction": 288,
    "extracted_at": "2025-09-08T07:18:34.630328"
  },
  "current_analysis": {
    "temperature_celsius": 9.5,
    "temperature_fahrenheit": 49.1,
    "feels_like_celsius": 8.7,
    "feels_like_fahrenheit": 47.7,
    "humidity_level": "Very High (Humid)",
    "weather_description": "Clear sky",
    "wind_description": "Light breeze",
    "comfort_index": "Uncomfortable",
    "precipitation_status": "No"
  },
  "forecast_data": [
    {
      "date": "2025-09-08",
      "city": "Toronto",
      "country": "Canada",
      "temp_max": 18.8,
      "temp_min": 8.7,
      "precipitation": 0.0,
      "weather_code": 1,
      "wind_speed_max": 16.9,
      "wind_direction": 241,
      "extracted_at": "2025-09-08T07:18:35.018524"
    },
    {
      "date": "2025-09-09",
      "city": "Toronto",
      "country": "Canada",
      "temp_max": 21.2,
      "temp_min": 13.6,
      "precipitation": 0.0,
      "weather_code": 3,
      "wind_speed_max": 13.7,
      "wind_direction": 115,
      "extracted_at": "2025-09-08T07:18:35.018537"
    },
    {
      "date": "2025-09-10",
      "city": "Toronto",
      "country": "Canada",
      "temp_max": 23.8,
      "temp_min": 15.6,
      "precipitation": 0.0,
      "weather_code": 3,
      "wind_speed_max": 12.4,
      "wind_direction": 134,
      "extracted_at": "2025-09-08T07:18:35.018540"
    },
    {
      "date": "2025-09-11",
      "city": "Toronto",
      "country": "Canada",
      "temp_max": 26.9,
      "temp_min": 16.4,
      "precipitation": 0.0,
      "weather_code": 3,
      "wind_speed_max": 17.1,
      "wind_direction": 353,
      "extracted_at": "2025-09-08T07:18:35.018543"
    },
    {
      "date": "2025-09-12",
      "city": "Toronto",
      "country": "Canada",
      "temp_max": 19.6,
      "temp_min": 15.2,
      "precipitation": 0.0,
      "weather_code": 3,
      "wind_speed_max": 21.4,
      "wind_direction": 77,
      "extracted_at": "2025-09-08T07:18:35.018546"
    },
    {
      "date": "2025-09-13",
      "city": "Toronto",
      "country": "Canada",
      "temp_max": 23.3,
      "temp_min": 16.2,
      "precipitation": 0.0,
      "weather_code": 3,
      "wind_speed_max": 14.0,
      "wind_direction": 81,
      "extracted_at": "2025-09-08T07:18:35.018549"
    },
    {
      "date": "2025-09-14",
      "city": "Toronto",
      "country": "Canada",
      "temp_max": 22.0,
      "temp_min": 17.4,
      "precipitation": 1.8,
      "weather_code": 51,
      "wind_speed_max": 12.8,
      "wind_direction": 84,
      "extracted_at": "2025-09-08T07:18:35.018552"
    }
  ],
  "forecast_analysis": {
    "temperature_trend": "Stable",
    "temperature_range": {
      "highest": 26.9,
      "lowest": 8.7,
      "average_high": 22.2,
      "average_low": 14.7
    },
    "precipitation_forecast": {
      "total_expected": 1.8,
      "rainy_days": 1,
      "heaviest_day": 1.8
    },
    "weather_summary": "1 clear day, 5 cloudy days, 1 rainy day",
    "alerts": [
      "No weather alerts"
    ]
  },
  "transformation_timestamp": "2025-09-08T07:18:35.020123",
  "data_quality": {
    "current_available": true,
    "forecast_available": true,
    "forecast_days": 7,
    "completeness": "Good"
  },
  "recorded_at": "2025-09-08T07:18:35.020265"
}