{
  "location": {
    "city": "Toronto",
    "country": "Canada",
    "latitude": 43.6532,
    "longitude": -79.3832
  },
  "extraction_info": {
    "timestamp": "2026-03-31T07:17:02.336021",
    "current_available": true,
    "forecast_days": 7,
    "source": "Open-Meteo API"
  },
  "current_weather": {
    "timestamp": "2026-03-31T03:15",
    "city": "Toronto",
    "country": "Canada",
    "latitude": 43.6532,
    "longitude": -79.3832,
    "temperature": 9.3,
    "feels_like": 8.4,
    "humidity": 99,
    "precipitation": 0.0,
    "weather_code": 45,
    "wind_speed": 4.6,
    "wind_direction": 162,
    "extracted_at": "2026-03-31T07:17:01.670852"
  },
  "current_analysis": {
    "temperature_celsius": 9.3,
    "temperature_fahrenheit": 48.7,
    "feels_like_celsius": 8.4,
    "feels_like_fahrenheit": 47.1,
    "humidity_level": "Very High (Humid)",
    "weather_description": "Fog",
    "wind_description": "Calm",
    "comfort_index": "Uncomfortable",
    "precipitation_status": "No"
  },
  "forecast_data": [
    {
      "date": "2026-03-31",
      "city": "Toronto",
      "country": "Canada",
      "temp_max": 11.5,
      "temp_min": 4.0,
      "precipitation": 6.68,
      "weather_code": 63,
      "wind_speed_max": 22.3,
      "wind_direction": 67,
      "extracted_at": "2026-03-31T07:17:02.334902"
    },
    {
      "date": "2026-04-01",
      "city": "Toronto",
      "country": "Canada",
      "temp_max": 6.4,
      "temp_min": 3.8,
      "precipitation": 1.5,
      "weather_code": 55,
      "wind_speed_max": 29.5,
      "wind_direction": 20,
      "extracted_at": "2026-03-31T07:17:02.334917"
    },
    {
      "date": "2026-04-02",
      "city": "Toronto",
      "country": "Canada",
      "temp_max": 4.1,
      "temp_min": 2.2,
      "precipitation": 0.3,
      "weather_code": 71,
      "wind_speed_max": 30.2,
      "wind_direction": 74,
      "extracted_at": "2026-03-31T07:17:02.334921"
    },
    {
      "date": "2026-04-03",
      "city": "Toronto",
      "country": "Canada",
      "temp_max": 20.8,
      "temp_min": 4.1,
      "precipitation": 0.8,
      "weather_code": 51,
      "wind_speed_max": 27.9,
      "wind_direction": 249,
      "extracted_at": "2026-03-31T07:17:02.334925"
    },
    {
      "date": "2026-04-04",
      "city": "Toronto",
      "country": "Canada",
      "temp_max": 9.0,
      "temp_min": 4.0,
      "precipitation": 4.1,
      "weather_code": 53,
      "wind_speed_max": 25.0,
      "wind_direction": 69,
      "extracted_at": "2026-03-31T07:17:02.334928"
    },
    {
      "date": "2026-04-05",
      "city": "Toronto",
      "country": "Canada",
      "temp_max": 11.9,
      "temp_min": 2.2,
      "precipitation": 1.8,
      "weather_code": 51,
      "wind_speed_max": 28.8,
      "wind_direction": 280,
      "extracted_at": "2026-03-31T07:17:02.334932"
    },
    {
      "date": "2026-04-06",
      "city": "Toronto",
      "country": "Canada",
      "temp_max": 7.4,
      "temp_min": -0.7,
      "precipitation": 0.0,
      "weather_code": 2,
      "wind_speed_max": 21.0,
      "wind_direction": 335,
      "extracted_at": "2026-03-31T07:17:02.334935"
    }
  ],
  "forecast_analysis": {
    "temperature_trend": "Warming trend",
    "temperature_range": {
      "highest": 20.8,
      "lowest": -0.7,
      "average_high": 10.2,
      "average_low": 2.8
    },
    "precipitation_forecast": {
      "total_expected": 15.2,
      "rainy_days": 6,
      "heaviest_day": 6.68
    },
    "weather_summary": "1 cloudy day, 6 rainy days, 1 snowy day",
    "alerts": [
      "No weather alerts"
    ]
  },
  "transformation_timestamp": "2026-03-31T07:17:02.336779",
  "data_quality": {
    "current_available": true,
    "forecast_available": true,
    "forecast_days": 7,
    "completeness": "Good"
  },
  "recorded_at": "2026-03-31T07:17:02.336942"
}