{
  "location": {
    "city": "Toronto",
    "country": "Canada",
    "latitude": 43.6532,
    "longitude": -79.3832
  },
  "extraction_info": {
    "timestamp": "2026-01-05T14:20:50.704804",
    "current_available": true,
    "forecast_days": 7,
    "source": "Open-Meteo API"
  },
  "current_weather": {
    "timestamp": "2026-01-05T09:15",
    "city": "Toronto",
    "country": "Canada",
    "latitude": 43.6532,
    "longitude": -79.3832,
    "temperature": -1.9,
    "feels_like": -7.3,
    "humidity": 90,
    "precipitation": 0.1,
    "weather_code": 73,
    "wind_speed": 19.4,
    "wind_direction": 165,
    "extracted_at": "2026-01-05T14:20:50.125324"
  },
  "current_analysis": {
    "temperature_celsius": -1.9,
    "temperature_fahrenheit": 28.6,
    "feels_like_celsius": -7.3,
    "feels_like_fahrenheit": 18.9,
    "humidity_level": "Very High (Humid)",
    "weather_description": "Moderate snow",
    "wind_description": "Moderate wind",
    "comfort_index": "Uncomfortable",
    "precipitation_status": "Yes"
  },
  "forecast_data": [
    {
      "date": "2026-01-05",
      "city": "Toronto",
      "country": "Canada",
      "temp_max": -0.6,
      "temp_min": -7.9,
      "precipitation": 2.9,
      "weather_code": 73,
      "wind_speed_max": 21.9,
      "wind_direction": 185,
      "extracted_at": "2026-01-05T14:20:50.703932"
    },
    {
      "date": "2026-01-06",
      "city": "Toronto",
      "country": "Canada",
      "temp_max": 2.6,
      "temp_min": -2.0,
      "precipitation": 10.7,
      "weather_code": 75,
      "wind_speed_max": 20.6,
      "wind_direction": 56,
      "extracted_at": "2026-01-05T14:20:50.703948"
    },
    {
      "date": "2026-01-07",
      "city": "Toronto",
      "country": "Canada",
      "temp_max": 1.9,
      "temp_min": -1.5,
      "precipitation": 0.9,
      "weather_code": 73,
      "wind_speed_max": 15.8,
      "wind_direction": 272,
      "extracted_at": "2026-01-05T14:20:50.703952"
    },
    {
      "date": "2026-01-08",
      "city": "Toronto",
      "country": "Canada",
      "temp_max": 4.3,
      "temp_min": 0.2,
      "precipitation": 0.0,
      "weather_code": 45,
      "wind_speed_max": 10.4,
      "wind_direction": 192,
      "extracted_at": "2026-01-05T14:20:50.703955"
    },
    {
      "date": "2026-01-09",
      "city": "Toronto",
      "country": "Canada",
      "temp_max": 10.5,
      "temp_min": 3.0,
      "precipitation": 11.6,
      "weather_code": 63,
      "wind_speed_max": 32.9,
      "wind_direction": 213,
      "extracted_at": "2026-01-05T14:20:50.703959"
    },
    {
      "date": "2026-01-10",
      "city": "Toronto",
      "country": "Canada",
      "temp_max": 3.2,
      "temp_min": 1.9,
      "precipitation": 1.2,
      "weather_code": 51,
      "wind_speed_max": 33.0,
      "wind_direction": 137,
      "extracted_at": "2026-01-05T14:20:50.703963"
    },
    {
      "date": "2026-01-11",
      "city": "Toronto",
      "country": "Canada",
      "temp_max": 1.7,
      "temp_min": -2.2,
      "precipitation": 0.0,
      "weather_code": 51,
      "wind_speed_max": 31.5,
      "wind_direction": 284,
      "extracted_at": "2026-01-05T14:20:50.703967"
    }
  ],
  "forecast_analysis": {
    "temperature_trend": "Warming trend",
    "temperature_range": {
      "highest": 10.5,
      "lowest": -7.9,
      "average_high": 3.4,
      "average_low": -1.2
    },
    "precipitation_forecast": {
      "total_expected": 27.3,
      "rainy_days": 5,
      "heaviest_day": 11.6
    },
    "weather_summary": "6 rainy days, 3 snowy days",
    "alerts": [
      "Heavy precipitation expected on 2026-01-06: 10.7mm",
      "Heavy precipitation expected on 2026-01-09: 11.6mm"
    ]
  },
  "transformation_timestamp": "2026-01-05T14:20:50.705467",
  "data_quality": {
    "current_available": true,
    "forecast_available": true,
    "forecast_days": 7,
    "completeness": "Good"
  },
  "recorded_at": "2026-01-05T14:20:50.705582"
}