{
  "location": {
    "city": "Toronto",
    "country": "Canada",
    "latitude": 43.6532,
    "longitude": -79.3832
  },
  "extraction_info": {
    "timestamp": "2025-09-18T11:25:44.309192",
    "current_available": true,
    "forecast_days": 7,
    "source": "Open-Meteo API"
  },
  "current_weather": {
    "timestamp": "2025-09-18T07:15",
    "city": "Toronto",
    "country": "Canada",
    "latitude": 43.6532,
    "longitude": -79.3832,
    "temperature": 12.9,
    "feels_like": 12.4,
    "humidity": 91,
    "precipitation": 0.0,
    "weather_code": 0,
    "wind_speed": 6.7,
    "wind_direction": 306,
    "extracted_at": "2025-09-18T11:25:43.898028"
  },
  "current_analysis": {
    "temperature_celsius": 12.9,
    "temperature_fahrenheit": 55.2,
    "feels_like_celsius": 12.4,
    "feels_like_fahrenheit": 54.3,
    "humidity_level": "Very High (Humid)",
    "weather_description": "Clear sky",
    "wind_description": "Light breeze",
    "comfort_index": "Acceptable",
    "precipitation_status": "No"
  },
  "forecast_data": [
    {
      "date": "2025-09-18",
      "city": "Toronto",
      "country": "Canada",
      "temp_max": 24.9,
      "temp_min": 13.0,
      "precipitation": 0.0,
      "weather_code": 1,
      "wind_speed_max": 18.7,
      "wind_direction": 293,
      "extracted_at": "2025-09-18T11:25:44.308038"
    },
    {
      "date": "2025-09-19",
      "city": "Toronto",
      "country": "Canada",
      "temp_max": 18.9,
      "temp_min": 12.6,
      "precipitation": 0.0,
      "weather_code": 3,
      "wind_speed_max": 13.8,
      "wind_direction": 4,
      "extracted_at": "2025-09-18T11:25:44.308054"
    },
    {
      "date": "2025-09-20",
      "city": "Toronto",
      "country": "Canada",
      "temp_max": 17.5,
      "temp_min": 12.3,
      "precipitation": 0.0,
      "weather_code": 3,
      "wind_speed_max": 23.1,
      "wind_direction": 76,
      "extracted_at": "2025-09-18T11:25:44.308059"
    },
    {
      "date": "2025-09-21",
      "city": "Toronto",
      "country": "Canada",
      "temp_max": 22.2,
      "temp_min": 16.3,
      "precipitation": 0.5,
      "weather_code": 51,
      "wind_speed_max": 25.6,
      "wind_direction": 95,
      "extracted_at": "2025-09-18T11:25:44.308065"
    },
    {
      "date": "2025-09-22",
      "city": "Toronto",
      "country": "Canada",
      "temp_max": 25.8,
      "temp_min": 18.3,
      "precipitation": 3.2,
      "weather_code": 53,
      "wind_speed_max": 28.1,
      "wind_direction": 204,
      "extracted_at": "2025-09-18T11:25:44.308070"
    },
    {
      "date": "2025-09-23",
      "city": "Toronto",
      "country": "Canada",
      "temp_max": 23.5,
      "temp_min": 18.3,
      "precipitation": 0.6,
      "weather_code": 51,
      "wind_speed_max": 13.0,
      "wind_direction": 166,
      "extracted_at": "2025-09-18T11:25:44.308075"
    },
    {
      "date": "2025-09-24",
      "city": "Toronto",
      "country": "Canada",
      "temp_max": 25.4,
      "temp_min": 18.3,
      "precipitation": 3.3,
      "weather_code": 53,
      "wind_speed_max": 8.9,
      "wind_direction": 152,
      "extracted_at": "2025-09-18T11:25:44.308080"
    }
  ],
  "forecast_analysis": {
    "temperature_trend": "Warming trend",
    "temperature_range": {
      "highest": 25.8,
      "lowest": 12.3,
      "average_high": 22.6,
      "average_low": 15.6
    },
    "precipitation_forecast": {
      "total_expected": 7.6,
      "rainy_days": 4,
      "heaviest_day": 3.3
    },
    "weather_summary": "1 clear day, 2 cloudy days, 4 rainy days",
    "alerts": [
      "No weather alerts"
    ]
  },
  "transformation_timestamp": "2025-09-18T11:25:44.309939",
  "data_quality": {
    "current_available": true,
    "forecast_available": true,
    "forecast_days": 7,
    "completeness": "Good"
  },
  "recorded_at": "2025-09-18T11:25:44.310124"
}