{
  "location": {
    "city": "Toronto",
    "country": "Canada",
    "latitude": 43.6532,
    "longitude": -79.3832
  },
  "extraction_info": {
    "timestamp": "2026-04-24T15:28:58.392275",
    "current_available": true,
    "forecast_days": 7,
    "source": "Open-Meteo API"
  },
  "current_weather": {
    "timestamp": "2026-04-24T11:15",
    "city": "Toronto",
    "country": "Canada",
    "latitude": 43.6532,
    "longitude": -79.3832,
    "temperature": 5.3,
    "feels_like": 0.2,
    "humidity": 76,
    "precipitation": 0.0,
    "weather_code": 3,
    "wind_speed": 24.3,
    "wind_direction": 75,
    "extracted_at": "2026-04-24T15:28:57.727074"
  },
  "current_analysis": {
    "temperature_celsius": 5.3,
    "temperature_fahrenheit": 41.5,
    "feels_like_celsius": 0.2,
    "feels_like_fahrenheit": 32.4,
    "humidity_level": "High",
    "weather_description": "Overcast",
    "wind_description": "Moderate wind",
    "comfort_index": "Uncomfortable",
    "precipitation_status": "No"
  },
  "forecast_data": [
    {
      "date": "2026-04-24",
      "city": "Toronto",
      "country": "Canada",
      "temp_max": 8.3,
      "temp_min": 4.7,
      "precipitation": 0.0,
      "weather_code": 3,
      "wind_speed_max": 24.2,
      "wind_direction": 63,
      "extracted_at": "2026-04-24T15:28:58.391375"
    },
    {
      "date": "2026-04-25",
      "city": "Toronto",
      "country": "Canada",
      "temp_max": 6.3,
      "temp_min": 4.0,
      "precipitation": 23.5,
      "weather_code": 63,
      "wind_speed_max": 35.1,
      "wind_direction": 49,
      "extracted_at": "2026-04-24T15:28:58.391389"
    },
    {
      "date": "2026-04-26",
      "city": "Toronto",
      "country": "Canada",
      "temp_max": 11.2,
      "temp_min": 4.0,
      "precipitation": 0.0,
      "weather_code": 3,
      "wind_speed_max": 17.1,
      "wind_direction": 67,
      "extracted_at": "2026-04-24T15:28:58.391392"
    },
    {
      "date": "2026-04-27",
      "city": "Toronto",
      "country": "Canada",
      "temp_max": 12.5,
      "temp_min": 6.1,
      "precipitation": 0.0,
      "weather_code": 3,
      "wind_speed_max": 25.0,
      "wind_direction": 86,
      "extracted_at": "2026-04-24T15:28:58.391395"
    },
    {
      "date": "2026-04-28",
      "city": "Toronto",
      "country": "Canada",
      "temp_max": 12.3,
      "temp_min": 8.2,
      "precipitation": 14.8,
      "weather_code": 80,
      "wind_speed_max": 25.8,
      "wind_direction": 137,
      "extracted_at": "2026-04-24T15:28:58.391398"
    },
    {
      "date": "2026-04-29",
      "city": "Toronto",
      "country": "Canada",
      "temp_max": 9.9,
      "temp_min": 4.0,
      "precipitation": 0.1,
      "weather_code": 51,
      "wind_speed_max": 17.6,
      "wind_direction": 279,
      "extracted_at": "2026-04-24T15:28:58.391401"
    },
    {
      "date": "2026-04-30",
      "city": "Toronto",
      "country": "Canada",
      "temp_max": 7.3,
      "temp_min": 3.5,
      "precipitation": 0.0,
      "weather_code": 45,
      "wind_speed_max": 21.8,
      "wind_direction": 324,
      "extracted_at": "2026-04-24T15:28:58.391404"
    }
  ],
  "forecast_analysis": {
    "temperature_trend": "Stable",
    "temperature_range": {
      "highest": 12.5,
      "lowest": 3.5,
      "average_high": 9.7,
      "average_low": 4.9
    },
    "precipitation_forecast": {
      "total_expected": 38.4,
      "rainy_days": 3,
      "heaviest_day": 23.5
    },
    "weather_summary": "3 cloudy days, 3 rainy days, 1 snowy day",
    "alerts": [
      "Heavy precipitation expected on 2026-04-25: 23.5mm",
      "Heavy precipitation expected on 2026-04-28: 14.8mm"
    ]
  },
  "transformation_timestamp": "2026-04-24T15:28:58.392951",
  "data_quality": {
    "current_available": true,
    "forecast_available": true,
    "forecast_days": 7,
    "completeness": "Good"
  },
  "recorded_at": "2026-04-24T15:28:58.393111"
}