{
  "location": {
    "city": "Toronto",
    "country": "Canada",
    "latitude": 43.6532,
    "longitude": -79.3832
  },
  "extraction_info": {
    "timestamp": "2025-09-05T20:15:27.821987",
    "current_available": true,
    "forecast_days": 7,
    "source": "Open-Meteo API"
  },
  "current_weather": {
    "timestamp": "2025-09-05T16:15",
    "city": "Toronto",
    "country": "Canada",
    "latitude": 43.6532,
    "longitude": -79.3832,
    "temperature": 21.7,
    "feels_like": 19.0,
    "humidity": 47,
    "precipitation": 0.0,
    "weather_code": 0,
    "wind_speed": 33.0,
    "wind_direction": 204,
    "extracted_at": "2025-09-05T20:15:27.421841"
  },
  "current_analysis": {
    "temperature_celsius": 21.7,
    "temperature_fahrenheit": 71.1,
    "feels_like_celsius": 19.0,
    "feels_like_fahrenheit": 66.2,
    "humidity_level": "Comfortable",
    "weather_description": "Clear sky",
    "wind_description": "Strong wind",
    "comfort_index": "Very Comfortable",
    "precipitation_status": "No"
  },
  "forecast_data": [
    {
      "date": "2025-09-05",
      "city": "Toronto",
      "country": "Canada",
      "temp_max": 22.2,
      "temp_min": 10.9,
      "precipitation": 0.0,
      "weather_code": 3,
      "wind_speed_max": 32.2,
      "wind_direction": 202,
      "extracted_at": "2025-09-05T20:15:27.820983"
    },
    {
      "date": "2025-09-06",
      "city": "Toronto",
      "country": "Canada",
      "temp_max": 19.5,
      "temp_min": 10.5,
      "precipitation": 0.0,
      "weather_code": 3,
      "wind_speed_max": 23.3,
      "wind_direction": 256,
      "extracted_at": "2025-09-05T20:15:27.820996"
    },
    {
      "date": "2025-09-07",
      "city": "Toronto",
      "country": "Canada",
      "temp_max": 19.8,
      "temp_min": 11.0,
      "precipitation": 0.1,
      "weather_code": 51,
      "wind_speed_max": 22.2,
      "wind_direction": 282,
      "extracted_at": "2025-09-05T20:15:27.820999"
    },
    {
      "date": "2025-09-08",
      "city": "Toronto",
      "country": "Canada",
      "temp_max": 19.2,
      "temp_min": 11.2,
      "precipitation": 0.0,
      "weather_code": 3,
      "wind_speed_max": 14.8,
      "wind_direction": 248,
      "extracted_at": "2025-09-05T20:15:27.821002"
    },
    {
      "date": "2025-09-09",
      "city": "Toronto",
      "country": "Canada",
      "temp_max": 21.4,
      "temp_min": 14.4,
      "precipitation": 0.0,
      "weather_code": 2,
      "wind_speed_max": 14.1,
      "wind_direction": 105,
      "extracted_at": "2025-09-05T20:15:27.821005"
    },
    {
      "date": "2025-09-10",
      "city": "Toronto",
      "country": "Canada",
      "temp_max": 25.9,
      "temp_min": 16.7,
      "precipitation": 0.0,
      "weather_code": 3,
      "wind_speed_max": 15.9,
      "wind_direction": 192,
      "extracted_at": "2025-09-05T20:15:27.821007"
    },
    {
      "date": "2025-09-11",
      "city": "Toronto",
      "country": "Canada",
      "temp_max": 24.0,
      "temp_min": 17.3,
      "precipitation": 0.3,
      "weather_code": 51,
      "wind_speed_max": 16.2,
      "wind_direction": 325,
      "extracted_at": "2025-09-05T20:15:27.821010"
    }
  ],
  "forecast_analysis": {
    "temperature_trend": "Warming trend",
    "temperature_range": {
      "highest": 25.9,
      "lowest": 10.5,
      "average_high": 21.7,
      "average_low": 13.1
    },
    "precipitation_forecast": {
      "total_expected": 0.4,
      "rainy_days": 2,
      "heaviest_day": 0.3
    },
    "weather_summary": "5 cloudy days, 2 rainy days",
    "alerts": [
      "No weather alerts"
    ]
  },
  "transformation_timestamp": "2025-09-05T20:15:27.822682",
  "data_quality": {
    "current_available": true,
    "forecast_available": true,
    "forecast_days": 7,
    "completeness": "Good"
  },
  "recorded_at": "2025-09-05T20:15:27.822814"
}