{
  "location": {
    "city": "Toronto",
    "country": "Canada",
    "latitude": 43.6532,
    "longitude": -79.3832
  },
  "extraction_info": {
    "timestamp": "2025-10-13T02:47:58.269226",
    "current_available": true,
    "forecast_days": 7,
    "source": "Open-Meteo API"
  },
  "current_weather": {
    "timestamp": "2025-10-12T22:45",
    "city": "Toronto",
    "country": "Canada",
    "latitude": 43.6532,
    "longitude": -79.3832,
    "temperature": 13.2,
    "feels_like": 11.5,
    "humidity": 76,
    "precipitation": 0.0,
    "weather_code": 0,
    "wind_speed": 10.4,
    "wind_direction": 70,
    "extracted_at": "2025-10-13T02:47:57.609629"
  },
  "current_analysis": {
    "temperature_celsius": 13.2,
    "temperature_fahrenheit": 55.8,
    "feels_like_celsius": 11.5,
    "feels_like_fahrenheit": 52.7,
    "humidity_level": "High",
    "weather_description": "Clear sky",
    "wind_description": "Light breeze",
    "comfort_index": "Acceptable",
    "precipitation_status": "No"
  },
  "forecast_data": [
    {
      "date": "2025-10-12",
      "city": "Toronto",
      "country": "Canada",
      "temp_max": 17.9,
      "temp_min": 10.9,
      "precipitation": 0.0,
      "weather_code": 3,
      "wind_speed_max": 23.0,
      "wind_direction": 50,
      "extracted_at": "2025-10-13T02:47:58.268452"
    },
    {
      "date": "2025-10-13",
      "city": "Toronto",
      "country": "Canada",
      "temp_max": 17.0,
      "temp_min": 12.1,
      "precipitation": 0.0,
      "weather_code": 3,
      "wind_speed_max": 22.7,
      "wind_direction": 73,
      "extracted_at": "2025-10-13T02:47:58.268462"
    },
    {
      "date": "2025-10-14",
      "city": "Toronto",
      "country": "Canada",
      "temp_max": 19.7,
      "temp_min": 8.7,
      "precipitation": 0.0,
      "weather_code": 3,
      "wind_speed_max": 20.1,
      "wind_direction": 331,
      "extracted_at": "2025-10-13T02:47:58.268465"
    },
    {
      "date": "2025-10-15",
      "city": "Toronto",
      "country": "Canada",
      "temp_max": 14.5,
      "temp_min": 9.3,
      "precipitation": 0.0,
      "weather_code": 3,
      "wind_speed_max": 18.5,
      "wind_direction": 354,
      "extracted_at": "2025-10-13T02:47:58.268468"
    },
    {
      "date": "2025-10-16",
      "city": "Toronto",
      "country": "Canada",
      "temp_max": 14.8,
      "temp_min": 6.9,
      "precipitation": 0.0,
      "weather_code": 3,
      "wind_speed_max": 13.4,
      "wind_direction": 7,
      "extracted_at": "2025-10-13T02:47:58.268471"
    },
    {
      "date": "2025-10-17",
      "city": "Toronto",
      "country": "Canada",
      "temp_max": 14.3,
      "temp_min": 9.1,
      "precipitation": 0.0,
      "weather_code": 3,
      "wind_speed_max": 12.6,
      "wind_direction": 125,
      "extracted_at": "2025-10-13T02:47:58.268474"
    },
    {
      "date": "2025-10-18",
      "city": "Toronto",
      "country": "Canada",
      "temp_max": 19.3,
      "temp_min": 12.6,
      "precipitation": 0.3,
      "weather_code": 51,
      "wind_speed_max": 18.1,
      "wind_direction": 194,
      "extracted_at": "2025-10-13T02:47:58.268477"
    }
  ],
  "forecast_analysis": {
    "temperature_trend": "Cooling trend",
    "temperature_range": {
      "highest": 19.7,
      "lowest": 6.9,
      "average_high": 16.8,
      "average_low": 9.9
    },
    "precipitation_forecast": {
      "total_expected": 0.3,
      "rainy_days": 1,
      "heaviest_day": 0.3
    },
    "weather_summary": "6 cloudy days, 1 rainy day",
    "alerts": [
      "No weather alerts"
    ]
  },
  "transformation_timestamp": "2025-10-13T02:47:58.270007",
  "data_quality": {
    "current_available": true,
    "forecast_available": true,
    "forecast_days": 7,
    "completeness": "Good"
  },
  "recorded_at": "2025-10-13T02:47:58.270129"
}