{
  "location": {
    "city": "Toronto",
    "country": "Canada",
    "latitude": 43.6532,
    "longitude": -79.3832
  },
  "extraction_info": {
    "timestamp": "2026-04-24T14:22:55.174585",
    "current_available": true,
    "forecast_days": 7,
    "source": "Open-Meteo API"
  },
  "current_weather": {
    "timestamp": "2026-04-24T10:15",
    "city": "Toronto",
    "country": "Canada",
    "latitude": 43.6532,
    "longitude": -79.3832,
    "temperature": 5.4,
    "feels_like": -0.1,
    "humidity": 75,
    "precipitation": 0.0,
    "weather_code": 3,
    "wind_speed": 25.1,
    "wind_direction": 78,
    "extracted_at": "2026-04-24T14:22:54.719762"
  },
  "current_analysis": {
    "temperature_celsius": 5.4,
    "temperature_fahrenheit": 41.7,
    "feels_like_celsius": -0.1,
    "feels_like_fahrenheit": 31.8,
    "humidity_level": "High",
    "weather_description": "Overcast",
    "wind_description": "Strong wind",
    "comfort_index": "Uncomfortable",
    "precipitation_status": "No"
  },
  "forecast_data": [
    {
      "date": "2026-04-24",
      "city": "Toronto",
      "country": "Canada",
      "temp_max": 8.3,
      "temp_min": 4.2,
      "precipitation": 1.8,
      "weather_code": 55,
      "wind_speed_max": 25.8,
      "wind_direction": 64,
      "extracted_at": "2026-04-24T14:22:55.173593"
    },
    {
      "date": "2026-04-25",
      "city": "Toronto",
      "country": "Canada",
      "temp_max": 6.3,
      "temp_min": 4.0,
      "precipitation": 25.6,
      "weather_code": 63,
      "wind_speed_max": 35.1,
      "wind_direction": 51,
      "extracted_at": "2026-04-24T14:22:55.173608"
    },
    {
      "date": "2026-04-26",
      "city": "Toronto",
      "country": "Canada",
      "temp_max": 11.2,
      "temp_min": 4.0,
      "precipitation": 0.0,
      "weather_code": 3,
      "wind_speed_max": 17.1,
      "wind_direction": 67,
      "extracted_at": "2026-04-24T14:22:55.173612"
    },
    {
      "date": "2026-04-27",
      "city": "Toronto",
      "country": "Canada",
      "temp_max": 12.5,
      "temp_min": 6.1,
      "precipitation": 0.0,
      "weather_code": 3,
      "wind_speed_max": 25.0,
      "wind_direction": 86,
      "extracted_at": "2026-04-24T14:22:55.173614"
    },
    {
      "date": "2026-04-28",
      "city": "Toronto",
      "country": "Canada",
      "temp_max": 12.3,
      "temp_min": 8.2,
      "precipitation": 14.8,
      "weather_code": 80,
      "wind_speed_max": 25.8,
      "wind_direction": 137,
      "extracted_at": "2026-04-24T14:22:55.173617"
    },
    {
      "date": "2026-04-29",
      "city": "Toronto",
      "country": "Canada",
      "temp_max": 9.9,
      "temp_min": 4.0,
      "precipitation": 0.1,
      "weather_code": 51,
      "wind_speed_max": 17.6,
      "wind_direction": 279,
      "extracted_at": "2026-04-24T14:22:55.173620"
    },
    {
      "date": "2026-04-30",
      "city": "Toronto",
      "country": "Canada",
      "temp_max": 7.3,
      "temp_min": 3.5,
      "precipitation": 0.0,
      "weather_code": 45,
      "wind_speed_max": 21.8,
      "wind_direction": 324,
      "extracted_at": "2026-04-24T14:22:55.173623"
    }
  ],
  "forecast_analysis": {
    "temperature_trend": "Stable",
    "temperature_range": {
      "highest": 12.5,
      "lowest": 3.5,
      "average_high": 9.7,
      "average_low": 4.9
    },
    "precipitation_forecast": {
      "total_expected": 42.3,
      "rainy_days": 4,
      "heaviest_day": 25.6
    },
    "weather_summary": "2 cloudy days, 4 rainy days, 1 snowy day",
    "alerts": [
      "Heavy precipitation expected on 2026-04-25: 25.6mm",
      "Heavy precipitation expected on 2026-04-28: 14.8mm"
    ]
  },
  "transformation_timestamp": "2026-04-24T14:22:55.175269",
  "data_quality": {
    "current_available": true,
    "forecast_available": true,
    "forecast_days": 7,
    "completeness": "Good"
  },
  "recorded_at": "2026-04-24T14:22:55.175405"
}